minhash.py
minhash-0.1.1.dist-info/LICENSE
minhash-0.1.1.dist-info/METADATA
minhash-0.1.1.dist-info/WHEEL
minhash-0.1.1.dist-info/top_level.txt
minhash-0.1.1.dist-info/RECORD
