Metadata-Version: 2.1
Name: minhash
Version: 0.1.1
Summary: A playground minhash implementation
Home-page: https://github.com/mattf/minhash
Author: Matthew Farrellee
Author-email: matt@cs.wisc.edu
License: UNKNOWN
Platform: UNKNOWN
Classifier: Programming Language :: Python :: 3
Classifier: License :: OSI Approved :: GNU Affero General Public License v3
Classifier: Operating System :: OS Independent
Requires-Python: >=3.6
Requires-Dist: numpy
Requires-Dist: gensim
Requires-Dist: mfoops
